{
    "SettingsVersion": 1.2,
    "SimMode": "Multirotor",
    "ViewMode": "NoDisplay",
    "ClockSpeed": 1,
    "LogMessagesVisible": false,
    "CameraDefaults": {
        "CaptureSettings": [
            {
                "ImageType": 0,
                "Width": 1920,
                "Height": 1080,
                "FOV_Degrees": 120,
                "AutoExposureSpeed": 100,
                "AutoExposureBias": 0,
                "AutoExposureMaxBrightness": 0.64,
                "AutoExposureMinBrightness": 0.03,
                "MotionBlurAmount": 0,
                "TargetGamma": 1.0,
                "ProjectionMode": "",
                "OrthoWidth": 5.12
            }
        ],
        "NoiseSettings": [
            {
                "Enabled": false,
                "ImageType": 0,
                "RandContrib": 0.2,
                "RandSpeed": 100000.0,
                "RandSize": 500.0,
                "RandDensity": 2,
                "HorzWaveContrib": 0.03,
                "HorzWaveStrength": 0.08,
                "HorzWaveVertSize": 1.0,
                "HorzWaveScreenSize": 1.0,
                "HorzNoiseLinesContrib": 1.0,
                "HorzNoiseLinesDensityY": 0.01,
                "HorzNoiseLinesDensityXY": 0.5,
                "HorzDistortionContrib": 1.0,
                "HorzDistortionStrength": 0.002
            }
        ]
    },
    "Vehicles" : {
        "Drone1" : {
            "VehicleType" : "SimpleFlight",
            "X": 0, "Y": 0, "Z": 0,
            "Yaw": 0,
            "Cameras" : {
                "high_res": {

                    "X": 0.0, "Y": 0.00, "Z": -0.20,
                    "Pitch": 0.0, "Roll": 0.0, "Yaw": 0.0
                }
            }
        }
    }
}
